{"status": 0, "data": [{"IPC": 0.0, "Callstack": "ffff0000082bac3c proc_pid_readdir+0x164 ([kernel.kallsyms])<-ffff0000082b5b70 proc_root_readdir+0x40 ([kernel.kallsyms])<-ffff00000825a070 iterate_dir+0x80 ([kernel.kallsyms])<-ffff00000825ad8c ksys_getdents64+0x8c ([kernel.kallsyms])<-ffff00000825ae98 __arm64_sys_getdents64+0x18 ([kernel.kallsyms])<-ffff00000809549c el0_svc_common+0x5c ([kernel.kallsyms])<-ffff000008095564 el0_svc_handler+0x24 ([kernel.kallsyms])<-ffff000008084108 el0_svc+0x8 ([kernel.kallsyms])<-fffeff46b330 [unknown] (/usr/lib64/libc-2.17.so)<-fffeff46b4cc [unknown] (/usr/lib64/libc-2.17.so)<-fffeffb88ef0 [unknown] (/usr/lib64/libmmpa.so)<-aaaae6821bd4 [unknown] (/var/IDE-daemon-device)<-aaaae6802554 [unknown] (/var/IDE-daemon-device)<-aaaae680336c [unknown] (/var/IDE-daemon-device)<-aaaae6803918 [unknown] (/var/IDE-daemon-device)<-aaaae680410c [unknown] (/var/IDE-daemon-device)<-aaaae6824590 [unknown] (/var/IDE-daemon-device)<-fffeff812bb0 [unknown] (/usr/lib64/libpthread-2.17.so)<-fffeff4a4b70 [unknown] (/usr/lib64/libc-2.17.so)", "Cycles": 16739764, "Retiring": 0.0, "Instructions": 0}]}
